libmonty/__init__.py
libmonty/__main__.py
libmonty/version.py
libmonty/environment/__init__.py
libmonty/environment/arguments.py
libmonty/environment/terminal.py
libmonty/fileformats/__init__.py
libmonty/fileformats/oab_process.py
libmonty/filesystem/__init__.py
libmonty/filesystem/copy_stubs.py
libmonty/filesystem/directory.py
libmonty/filesystem/tree_exec.py
libmonty/formatting/__init__.py
libmonty/formatting/char_str.py
libmonty/formatting/debugging.py
libmonty/formatting/json.py
libmonty/formatting/number_str.py
libmonty/images/__init__.py
libmonty/images/colors_named.py
libmonty/images/convert_from_stream.py
libmonty/network/__init__.py
libmonty/network/email_check.py
libmonty/network/responses.py
libmonty/outpututils/__init__.py
libmonty/outpututils/asciistyling.py
libmonty/outpututils/decorators.py
libmonty/outpututils/discord.py
libmonty/sound/__init__.py
libmonty/sound/formats/__init__.py
libmonty/sound/formats/wave_pcm.py
libmonty-0.1.1.dist-info/LICENSE
libmonty-0.1.1.dist-info/METADATA
libmonty-0.1.1.dist-info/WHEEL
libmonty-0.1.1.dist-info/entry_points.txt
libmonty-0.1.1.dist-info/top_level.txt
libmonty-0.1.1.dist-info/RECORD
