Metadata-Version: 2.1
Name: libmonty
Version: 0.1.1
Summary: libmonty - a collection of Python libraries
Home-page: https://codeberg.org/sunarch/libmonty
Author: András Németh (sunarch)
Author-email: sunarch@protonmail.com
Maintainer: András Németh (sunarch)
Maintainer-email: sunarch@protonmail.com
License: Mozilla Public License 2.0 (MPL 2.0)
Project-URL: Bug Tracker, https://codeberg.org/sunarch/libmonty/issues
Keywords: libmonty
Platform: Any
Classifier: Programming Language :: Python :: 3
Classifier: License :: OSI Approved :: Mozilla Public License 2.0 (MPL 2.0)
Classifier: Operating System :: OS Independent
Classifier: Development Status :: 3 - Alpha
Classifier: Intended Audience :: Developers
Classifier: Intended Audience :: End Users/Desktop
Classifier: Topic :: Utilities
Classifier: Topic :: Multimedia :: Sound/Audio :: Players
Classifier: Typing :: Typed
Requires-Python: >=3.9
License-File: LICENSE
Requires-Dist: email-validator ==2.2.0
Requires-Dist: libmonty-logging ==0.2.0
Requires-Dist: numpy ==2.0.0
Requires-Dist: pillow ==10.3.0
Requires-Dist: tqdm ==4.66.4
Requires-Dist: pygame ==2.6.0
